autimacy/__devel__.py
autimacy/__init__.py
autimacy/__sane__.py
autimacy-0.1.0.dist-info/WHEEL
autimacy-0.1.0.dist-info/WHEEL.json
autimacy-0.1.0.dist-info/entry_points.txt
autimacy-0.1.0.dist-info/METADATA
autimacy-0.1.0.dist-info/METADATA.json
autimacy-0.1.0.dist-info/RECORD
