Metadata-Version: 2.3
Name: autimacy
Version: 0.1.0
Summary: logging with to much information
Classifier: Programming Language :: Python :: 3
Classifier: License :: OSI Approved :: MIT License
Classifier: Operating System :: OS Independent
Classifier: Development Status :: 1 - Planning
Classifier: Intended Audience :: Developers
Requires-Dist: parlancy>=0.1.1
Requires-Dist: langchain>=1.2.4
Requires-Python: >=3.12
